{
  "kind": "collectionType",
  "collectionName": "deals",
  "info": {
    "singularName": "deal",
    "pluralName": "deals",
    "displayName": "deal"
  },
  "options": {
    "draftAndPublish": true
  },
  "pluginOptions": {},
  "attributes": {
    "dealName": {
      "type": "string",
      "required": true
    },
    "referenceNumber": {
      "type": "string",
      "required": true
    },
    "startDate": {
      "type": "date",
      "required": true
    },
    "endDate": {
      "type": "date",
      "required": true
    },
    "roomType": {
      "type": "string",
      "required": true
    },
    "statusDeal": {
      "type": "string",
      "required": true
    },
    "reservationsLeft": {
      "type": "integer",
      "required": true
    }
  }
}
